{
    "FEATURECLA": "Admin-1 scale rank",
    "SCALERANK": 2,
    "ADM1_CODE": "RUS-3200",
    "DISS_ME": 3200,
    "ISO_3166_2": "RU-PER",
    "WIKIPEDIA": null,
    "ISO_A2": "RU",
    "ADM0_SR": 1,
    "NAME": "Perm'",
    "NAME_ALT": "Molotov|Permskaya Oblast",
    "NAME_LOCAL": "Пермская область",
    "TYPE": "Kray",
    "TYPE_EN": "Territory",
    "CODE_LOCAL": null,
    "CODE_HASC": "RU.PE",
    "NOTE": null,
    "HASC_MAYBE": null,
    "REGION": "Volga",
    "REGION_COD": null,
    "PROVNUM_NE": 20007,
    "GADM_LEVEL": 1,
    "CHECK_ME": 20,
    "DATARANK": 2,
    "ABBREV": null,
    "POSTAL": "PE",
    "AREA_SQKM": 0,
    "SAMEASCITY": 6,
    "LABELRANK": 6,
    "NAME_LEN": 5,
    "MAPCOLOR9": 7,
    "MAPCOLOR13": 7,
    "FIPS": "RS90",
    "FIPS_ALT": null,
    "WOE_ID": 20070511,
    "WOE_LABEL": "Permskiy Kray, RU, Russia",
    "WOE_NAME": "Perm'",
    "LATITUDE": 58.8735,
    "LONGITUDE": 56.5878,
    "SOV_A3": "RUS",
    "ADM0_A3": "RUS",
    "ADM0_LABEL": 2,
    "ADMIN": "Russia",
    "GEONUNIT": "Russia",
    "GU_A3": "RUS",
    "GN_ID": 511180,
    "GN_NAME": "Perm Krai",
    "GNS_ID": 9262371,
    "GNS_NAME": "Permskiy Kray",
    "GN_LEVEL": 1,
    "GN_REGION": null,
    "GN_A1_CODE": "RU.90",
    "REGION_SUB": "Urals",
    "SUB_CODE": null,
    "GNS_LEVEL": 1,
    "GNS_LANG": "dan",
    "GNS_ADM1": "RS90",
    "GNS_REGION": null,
    "MIN_LABEL": 5,
    "MAX_LABEL": 10.2,
    "MIN_ZOOM": 4.7,
    "WIKIDATAID": "Q5400",
    "NAME_AR": "بيرم كراي",
    "NAME_BN": "পেরম ক্রায়",
    "NAME_DE": "Region Perm",
    "NAME_EN": "Perm Krai",
    "NAME_ES": "Perm",
    "NAME_FR": "Kraï de Perm",
    "NAME_EL": "Κράι Περμ",
    "NAME_HI": "पेर्म क्राय",
    "NAME_HU": "Permi határterület",
    "NAME_ID": "Krai Perm",
    "NAME_IT": "Territorio di Perm'",
    "NAME_JA": "ペルミ地方",
    "NAME_KO": "페름 지방",
    "NAME_NL": "Kraj Perm",
    "NAME_PL": "Kraj Permski",
    "NAME_PT": "Krai de Perm",
    "NAME_RU": "Пермский край",
    "NAME_SV": "Perm kraj",
    "NAME_TR": "Perm Krayı",
    "NAME_VI": "Perm",
    "NAME_ZH": "彼爾姆邊疆區",
    "NE_ID": 1159314843
}