{
    "FEATURECLA": "Admin-1 scale rank",
    "SCALERANK": 4,
    "ADM1_CODE": "AGO-1874",
    "DISS_ME": 1874,
    "ISO_3166_2": "AO-LNO",
    "WIKIPEDIA": null,
    "ISO_A2": "AO",
    "ADM0_SR": 1,
    "NAME": "Lunda Norte",
    "NAME_ALT": null,
    "NAME_LOCAL": null,
    "TYPE": "Província",
    "TYPE_EN": "Province",
    "CODE_LOCAL": null,
    "CODE_HASC": "AO.LN",
    "NOTE": null,
    "HASC_MAYBE": null,
    "REGION": null,
    "REGION_COD": null,
    "PROVNUM_NE": 18,
    "GADM_LEVEL": 1,
    "CHECK_ME": 0,
    "DATARANK": 6,
    "ABBREV": null,
    "POSTAL": "LN",
    "AREA_SQKM": 0,
    "SAMEASCITY": -99,
    "LABELRANK": 4,
    "NAME_LEN": 11,
    "MAPCOLOR9": 6,
    "MAPCOLOR13": 1,
    "FIPS": "AO17",
    "FIPS_ALT": null,
    "WOE_ID": 2344671,
    "WOE_LABEL": null,
    "WOE_NAME": "Lunda Norte",
    "LATITUDE": -8.4722,
    "LONGITUDE": 19.6268,
    "SOV_A3": "AGO",
    "ADM0_A3": "AGO",
    "ADM0_LABEL": 2,
    "ADMIN": "Angola",
    "GEONUNIT": "Angola",
    "GU_A3": "AGO",
    "GN_ID": 145702,
    "GN_NAME": "Lunda Norte Province",
    "GNS_ID": -2866812,
    "GNS_NAME": "Lunda Norte, Provincia da",
    "GN_LEVEL": 1,
    "GN_REGION": null,
    "GN_A1_CODE": "AO.17",
    "REGION_SUB": null,
    "SUB_CODE": null,
    "GNS_LEVEL": 1,
    "GNS_LANG": "rus",
    "GNS_ADM1": "AO17",
    "GNS_REGION": null,
    "MIN_LABEL": 6.6,
    "MAX_LABEL": 11,
    "MIN_ZOOM": 6.6,
    "WIKIDATAID": "Q214221",
    "NAME_AR": "مقاطعة لوندا نورتي",
    "NAME_BN": "লুন্ডা নর্টে প্রদেশ",
    "NAME_DE": "Provinz Lunda Norte",
    "NAME_EN": "Lunda Norte Province",
    "NAME_ES": "Lunda Norte",
    "NAME_FR": "Lunda-Nord",
    "NAME_EL": "Λούντα Νόρτε",
    "NAME_HI": "लुंडा नोर्टे प्रांत",
    "NAME_HU": null,
    "NAME_ID": "Provinsi Lunda Norte",
    "NAME_IT": "provincia di Lunda Nord",
    "NAME_JA": "ルンダ・ノルテ州",
    "NAME_KO": "룬다노르트 주",
    "NAME_NL": "Lunda Norte",
    "NAME_PL": "Prowincja Lunda Północna",
    "NAME_PT": "Lunda-Norte",
    "NAME_RU": "Северная Лунда",
    "NAME_SV": "Lunda Norte",
    "NAME_TR": "Lunda Norte Bölgesi",
    "NAME_VI": "Lunda Norte",
    "NAME_ZH": "北倫達省",
    "NE_ID": 1159311281
}