{
    "FEATURECLA": "Admin-1 scale rank",
    "SCALERANK": 4,
    "ADM1_CODE": "ZMB-515",
    "DISS_ME": 515,
    "ISO_3166_2": "ZM-05",
    "WIKIPEDIA": null,
    "ISO_A2": "ZM",
    "ADM0_SR": 1,
    "NAME": "Northern",
    "NAME_ALT": null,
    "NAME_LOCAL": null,
    "TYPE": "Province",
    "TYPE_EN": "Province",
    "CODE_LOCAL": null,
    "CODE_HASC": "ZM.NR",
    "NOTE": null,
    "HASC_MAYBE": null,
    "REGION": null,
    "REGION_COD": null,
    "PROVNUM_NE": 4,
    "GADM_LEVEL": 1,
    "CHECK_ME": 0,
    "DATARANK": 6,
    "ABBREV": null,
    "POSTAL": "NO",
    "AREA_SQKM": 0,
    "SAMEASCITY": -99,
    "LABELRANK": 4,
    "NAME_LEN": 8,
    "MAPCOLOR9": 5,
    "MAPCOLOR13": 13,
    "FIPS": "ZA05",
    "FIPS_ALT": null,
    "WOE_ID": 2347807,
    "WOE_LABEL": "Northern, ZM, Zambia",
    "WOE_NAME": "Northern",
    "LATITUDE": -9.79906,
    "LONGITUDE": 30.7539,
    "SOV_A3": "ZMB",
    "ADM0_A3": "ZMB",
    "ADM0_LABEL": 2,
    "ADMIN": "Zambia",
    "GEONUNIT": "Zambia",
    "GU_A3": "ZMB",
    "GN_ID": 900601,
    "GN_NAME": "Northern Province",
    "GNS_ID": -2301341,
    "GNS_NAME": "Northern",
    "GN_LEVEL": 1,
    "GN_REGION": null,
    "GN_A1_CODE": "ZM.05",
    "REGION_SUB": null,
    "SUB_CODE": null,
    "GNS_LEVEL": 1,
    "GNS_LANG": "eng",
    "GNS_ADM1": "ZA05",
    "GNS_REGION": null,
    "MIN_LABEL": 6.6,
    "MAX_LABEL": 11,
    "MIN_ZOOM": 6.6,
    "WIKIDATAID": "Q778738",
    "NAME_AR": "المحافظة الشمالية، زامبيا",
    "NAME_BN": "নর্দান প্রদেশ",
    "NAME_DE": "Nordprovinz",
    "NAME_EN": "Northern Province",
    "NAME_ES": "Provincia del Norte",
    "NAME_FR": "Province Septentrionale",
    "NAME_EL": "Βόρεια Επαρχία",
    "NAME_HI": "उत्तरी प्रांत",
    "NAME_HU": null,
    "NAME_ID": "Provinsi Utara",
    "NAME_IT": "provincia Settentrionale",
    "NAME_JA": "北部州",
    "NAME_KO": "북부 주",
    "NAME_NL": "Northern",
    "NAME_PL": "Prowincja Północna",
    "NAME_PT": "Província do Norte",
    "NAME_RU": "Северная провинция",
    "NAME_SV": "Northern",
    "NAME_TR": "Kuzey Bölgesi",
    "NAME_VI": "Tỉnh Phía Bắc",
    "NAME_ZH": "北方省",
    "NE_ID": 1159307879
}