{
    "FEATURECLA": "Admin-0 country",
    "SCALERANK": 5,
    "LABELRANK": 4,
    "SOVEREIGNT": "Tonga",
    "SOV_A3": "TON",
    "ADM0_DIF": 0,
    "LEVEL": 2,
    "TYPE": "Sovereign country",
    "ADMIN": "Tonga",
    "ADM0_A3": "TON",
    "GEOU_DIF": 0,
    "GEOUNIT": "Tonga",
    "GU_A3": "TON",
    "SU_DIF": 0,
    "SUBUNIT": "Tonga",
    "SU_A3": "TON",
    "BRK_DIFF": 0,
    "NAME": "Tonga",
    "NAME_LONG": "Tonga",
    "BRK_A3": "TON",
    "BRK_NAME": "Tonga",
    "BRK_GROUP": null,
    "ABBREV": "Tongo",
    "POSTAL": "TO",
    "FORMAL_EN": "Kingdom of Tonga",
    "FORMAL_FR": null,
    "NAME_CIAWF": "Tonga",
    "NOTE_ADM0": null,
    "NOTE_BRK": null,
    "NAME_SORT": "Tonga",
    "NAME_ALT": null,
    "MAPCOLOR7": 2,
    "MAPCOLOR8": 1,
    "MAPCOLOR9": 1,
    "MAPCOLOR13": 8,
    "POP_EST": 106479,
    "POP_RANK": 9,
    "GDP_MD_EST": 557,
    "POP_YEAR": 2017,
    "LASTCENSUS": 2006,
    "GDP_YEAR": 2016,
    "ECONOMY": "6. Developing region",
    "INCOME_GRP": "4. Lower middle income",
    "WIKIPEDIA": -99,
    "FIPS_10_": "TN",
    "ISO_A2": "TO",
    "ISO_A3": "TON",
    "ISO_A3_EH": "TON",
    "ISO_N3": "776",
    "UN_A3": "776",
    "WB_A2": "TO",
    "WB_A3": "TON",
    "WOE_ID": 23424964,
    "WOE_ID_EH": 23424964,
    "WOE_NOTE": "Exact WOE match as country",
    "ADM0_A3_IS": "TON",
    "ADM0_A3_US": "TON",
    "ADM0_A3_UN": -99,
    "ADM0_A3_WB": -99,
    "CONTINENT": "Oceania",
    "REGION_UN": "Oceania",
    "SUBREGION": "Polynesia",
    "REGION_WB": "East Asia & Pacific",
    "NAME_LEN": 5,
    "LONG_LEN": 5,
    "ABBREV_LEN": 5,
    "TINY": 3,
    "HOMEPART": 1,
    "MIN_ZOOM": 0,
    "MIN_LABEL": 4,
    "MAX_LABEL": 9,
    "NE_ID": 1159321319,
    "WIKIDATAID": "Q678",
    "NAME_AR": "تونغا",
    "NAME_BN": "টোঙ্গা",
    "NAME_DE": "Tonga",
    "NAME_EN": "Tonga",
    "NAME_ES": "Tonga",
    "NAME_FR": "Tonga",
    "NAME_EL": "Τόνγκα",
    "NAME_HI": "टोंगा",
    "NAME_HU": "Tonga",
    "NAME_ID": "Tonga",
    "NAME_IT": "Tonga",
    "NAME_JA": "トンガ",
    "NAME_KO": "통가",
    "NAME_NL": "Tonga",
    "NAME_PL": "Tonga",
    "NAME_PT": "Tonga",
    "NAME_RU": "Тонга",
    "NAME_SV": "Tonga",
    "NAME_TR": "Tonga",
    "NAME_VI": "Tonga",
    "NAME_ZH": "東加"
}