{
    "FEATURECLA": "Admin-1 aggregation",
    "SCALERANK": 10,
    "ADM1_CODE": "MLT-5920",
    "DISS_ME": 5920,
    "ISO_3166_2": "MT-01",
    "WIKIPEDIA": null,
    "ISO_A2": "MT",
    "ADM0_SR": 3,
    "NAME": "Attard",
    "NAME_ALT": null,
    "NAME_LOCAL": null,
    "TYPE": null,
    "TYPE_EN": null,
    "CODE_LOCAL": null,
    "CODE_HASC": "MT.CE.AT",
    "NOTE": null,
    "HASC_MAYBE": null,
    "REGION": "Malta Majjistral",
    "REGION_COD": null,
    "PROVNUM_NE": 0,
    "GADM_LEVEL": 0,
    "CHECK_ME": 0,
    "DATARANK": 10,
    "ABBREV": null,
    "POSTAL": null,
    "AREA_SQKM": 0,
    "SAMEASCITY": -99,
    "LABELRANK": 20,
    "NAME_LEN": 6,
    "MAPCOLOR9": 1,
    "MAPCOLOR13": 8,
    "FIPS": null,
    "FIPS_ALT": null,
    "WOE_ID": 24551373,
    "WOE_LABEL": null,
    "WOE_NAME": "Malta",
    "LATITUDE": 35.8878,
    "LONGITUDE": 14.4318,
    "SOV_A3": "MLT",
    "ADM0_A3": "MLT",
    "ADM0_LABEL": 5,
    "ADMIN": "Malta",
    "GEONUNIT": "Malta",
    "GU_A3": "MLT",
    "GN_ID": 8299700,
    "GN_NAME": "Attard",
    "GNS_ID": 11534002,
    "GNS_NAME": "H'Attard",
    "GN_LEVEL": 1,
    "GN_REGION": null,
    "GN_A1_CODE": "MT.01",
    "REGION_SUB": "Western",
    "SUB_CODE": null,
    "GNS_LEVEL": 1,
    "GNS_LANG": "mlt",
    "GNS_ADM1": "MT01",
    "GNS_REGION": null,
    "MIN_LABEL": 11,
    "MAX_LABEL": 11,
    "MIN_ZOOM": 11,
    "WIKIDATAID": "Q44557",
    "NAME_AR": "عطار",
    "NAME_BN": "আতার্ড",
    "NAME_DE": "Attard",
    "NAME_EN": "Attard",
    "NAME_ES": "Attard",
    "NAME_FR": "Attard",
    "NAME_EL": "Ατάρντ",
    "NAME_HI": "अटार्ड",
    "NAME_HU": "Attard",
    "NAME_ID": "Attard",
    "NAME_IT": "Attard",
    "NAME_JA": "アタード",
    "NAME_KO": "아타르트",
    "NAME_NL": "Attard",
    "NAME_PL": "Attard",
    "NAME_PT": "Attard",
    "NAME_RU": "Аттард",
    "NAME_SV": "Attard",
    "NAME_TR": "Attard",
    "NAME_VI": "Attard",
    "NAME_ZH": "阿塔爾德",
    "NE_ID": 1159315585
}