{
    "FEATURECLA": "Admin-1 scale rank",
    "SCALERANK": 10,
    "ADM1_CODE": "SVN-1016",
    "DISS_ME": 1016,
    "ISO_3166_2": "SI-102",
    "WIKIPEDIA": null,
    "ISO_A2": "SI",
    "ADM0_SR": 1,
    "NAME": "Radovljica",
    "NAME_ALT": null,
    "NAME_LOCAL": null,
    "TYPE": "Statisticna Regije",
    "TYPE_EN": "Statistical Region",
    "CODE_LOCAL": null,
    "CODE_HASC": "SI.GO.RA",
    "NOTE": null,
    "HASC_MAYBE": null,
    "REGION": "Gorenjska",
    "REGION_COD": null,
    "PROVNUM_NE": 161,
    "GADM_LEVEL": 2,
    "CHECK_ME": 0,
    "DATARANK": 8,
    "ABBREV": null,
    "POSTAL": "GO",
    "AREA_SQKM": 0,
    "SAMEASCITY": -99,
    "LABELRANK": 10,
    "NAME_LEN": 10,
    "MAPCOLOR9": 2,
    "MAPCOLOR13": 12,
    "FIPS": "SIA3",
    "FIPS_ALT": null,
    "WOE_ID": 55848379,
    "WOE_LABEL": null,
    "WOE_NAME": "Radovljica",
    "LATITUDE": 46.3361,
    "LONGITUDE": 14.1929,
    "SOV_A3": "SVN",
    "ADM0_A3": "SVN",
    "ADM0_LABEL": 2,
    "ADMIN": "Slovenia",
    "GEONUNIT": "Slovenia",
    "GU_A3": "SVN",
    "GN_ID": 3192062,
    "GN_NAME": "Obcina Radovljica",
    "GNS_ID": -93715,
    "GNS_NAME": "Radovljica, Obcina",
    "GN_LEVEL": 1,
    "GN_REGION": null,
    "GN_A1_CODE": "SI.A3",
    "REGION_SUB": null,
    "SUB_CODE": null,
    "GNS_LEVEL": 1,
    "GNS_LANG": "mkd",
    "GNS_ADM1": "SI86",
    "GNS_REGION": null,
    "MIN_LABEL": 11,
    "MAX_LABEL": 11,
    "MIN_ZOOM": 11,
    "WIKIDATAID": "Q15910",
    "NAME_AR": "بلدية رادوفلييكا",
    "NAME_BN": "র‍্যাদোভ্লজিকা পৌরসভা",
    "NAME_DE": "Radovljica",
    "NAME_EN": "Radovljica Municipality",
    "NAME_ES": "Radovljica",
    "NAME_FR": "Radovljica",
    "NAME_EL": "Ραντοβλτζίκα",
    "NAME_HI": "राडोवलिका नगरपालिका",
    "NAME_HU": null,
    "NAME_ID": "Kotamadya Radovljica",
    "NAME_IT": "Radovljica",
    "NAME_JA": "ラドヴリツァ",
    "NAME_KO": "라도블리차",
    "NAME_NL": "Radovljica",
    "NAME_PL": "Radovljica Municipality",
    "NAME_PT": "Radovljica",
    "NAME_RU": "Радовлица",
    "NAME_SV": "Radovljica",
    "NAME_TR": "Radovljica Belediyesi",
    "NAME_VI": "Đô thị tự trị Radovljica",
    "NAME_ZH": "拉多夫利察",
    "NE_ID": 1159310839
}