{
    "FEATURECLA": "Admin-1 scale rank",
    "SCALERANK": 7,
    "ADM1_CODE": "PRT-743",
    "DISS_ME": 743,
    "ISO_3166_2": "PT-02",
    "WIKIPEDIA": null,
    "ISO_A2": "PT",
    "ADM0_SR": 1,
    "NAME": "Beja",
    "NAME_ALT": null,
    "NAME_LOCAL": null,
    "TYPE": "Distrito",
    "TYPE_EN": "District",
    "CODE_LOCAL": null,
    "CODE_HASC": "PT.BE",
    "NOTE": null,
    "HASC_MAYBE": null,
    "REGION": "Alentejo",
    "REGION_COD": null,
    "PROVNUM_NE": 16,
    "GADM_LEVEL": 1,
    "CHECK_ME": 20,
    "DATARANK": 6,
    "ABBREV": null,
    "POSTAL": "BE",
    "AREA_SQKM": 0,
    "SAMEASCITY": 7,
    "LABELRANK": 7,
    "NAME_LEN": 4,
    "MAPCOLOR9": 1,
    "MAPCOLOR13": 4,
    "FIPS": "PO03",
    "FIPS_ALT": null,
    "WOE_ID": 2346563,
    "WOE_LABEL": "Beja, PT, Portugal",
    "WOE_NAME": "Beja",
    "LATITUDE": 37.8511,
    "LONGITUDE": -7.88716,
    "SOV_A3": "PRT",
    "ADM0_A3": "PRT",
    "ADM0_LABEL": 2,
    "ADMIN": "Portugal",
    "GEONUNIT": "Portugal",
    "GU_A3": "PRX",
    "GN_ID": 2270984,
    "GN_NAME": "Distrito de Beja",
    "GNS_ID": -2159656,
    "GNS_NAME": "Beja, Distrito de",
    "GN_LEVEL": 1,
    "GN_REGION": null,
    "GN_A1_CODE": "PT.03",
    "REGION_SUB": null,
    "SUB_CODE": null,
    "GNS_LEVEL": 1,
    "GNS_LANG": "fra",
    "GNS_ADM1": "PO03",
    "GNS_REGION": null,
    "MIN_LABEL": 8,
    "MAX_LABEL": 11,
    "MIN_ZOOM": 7.7,
    "WIKIDATAID": "Q321455",
    "NAME_AR": "محافظة بيجا",
    "NAME_BN": "বেজা জেলা",
    "NAME_DE": "Distrikt Beja",
    "NAME_EN": "Beja District",
    "NAME_ES": "Distrito de Beja",
    "NAME_FR": "District de Beja",
    "NAME_EL": "Μπέτζα",
    "NAME_HI": "बेजा जिला",
    "NAME_HU": "Beja",
    "NAME_ID": "Distrik Beja",
    "NAME_IT": "distretto di Beja",
    "NAME_JA": "ベージャ県",
    "NAME_KO": "베자 현",
    "NAME_NL": "Beja",
    "NAME_PL": "Dystrykt Beja",
    "NAME_PT": "Distrito de Beja",
    "NAME_RU": "Бежа",
    "NAME_SV": "Beja",
    "NAME_TR": "Beja District",
    "NAME_VI": "Beja",
    "NAME_ZH": "貝雅區",
    "NE_ID": 1159310567
}