{
    "FEATURECLA": "Admin-1 scale rank",
    "SCALERANK": 8,
    "ADM1_CODE": "NLD-903",
    "DISS_ME": 903,
    "ISO_3166_2": "NL-ZE",
    "WIKIPEDIA": null,
    "ISO_A2": "NL",
    "ADM0_SR": 1,
    "NAME": "Zeeland",
    "NAME_ALT": "Zelanda|Zélande|Zelândia",
    "NAME_LOCAL": null,
    "TYPE": "Provincie",
    "TYPE_EN": "Province",
    "CODE_LOCAL": null,
    "CODE_HASC": "NL.ZE",
    "NOTE": null,
    "HASC_MAYBE": null,
    "REGION": null,
    "REGION_COD": null,
    "PROVNUM_NE": 1,
    "GADM_LEVEL": 1,
    "CHECK_ME": 20,
    "DATARANK": 8,
    "ABBREV": null,
    "POSTAL": "ZE",
    "AREA_SQKM": 0,
    "SAMEASCITY": -99,
    "LABELRANK": 8,
    "NAME_LEN": 7,
    "MAPCOLOR9": 2,
    "MAPCOLOR13": 9,
    "FIPS": "NL10",
    "FIPS_ALT": null,
    "WOE_ID": 2346382,
    "WOE_LABEL": "Zeeland, NL, Netherlands",
    "WOE_NAME": "Zeeland",
    "LATITUDE": 51.2837,
    "LONGITUDE": 3.78515,
    "SOV_A3": "NL1",
    "ADM0_A3": "NLD",
    "ADM0_LABEL": 6,
    "ADMIN": "Netherlands",
    "GEONUNIT": null,
    "GU_A3": "NLD",
    "GN_ID": 2744011,
    "GN_NAME": "Provincie Zeeland",
    "GNS_ID": -2156287,
    "GNS_NAME": "Zeeland, Provincie",
    "GN_LEVEL": 1,
    "GN_REGION": null,
    "GN_A1_CODE": "NL.10",
    "REGION_SUB": null,
    "SUB_CODE": null,
    "GNS_LEVEL": 1,
    "GNS_LANG": "fra",
    "GNS_ADM1": "NL10",
    "GNS_REGION": null,
    "MIN_LABEL": 8,
    "MAX_LABEL": 11,
    "MIN_ZOOM": 8,
    "WIKIDATAID": "Q705",
    "NAME_AR": "زيلند",
    "NAME_BN": "জিল্যান্ড",
    "NAME_DE": "Zeeland",
    "NAME_EN": "Zeeland",
    "NAME_ES": "Zelanda",
    "NAME_FR": "Zélande",
    "NAME_EL": "Ζηλανδία",
    "NAME_HI": "ज़ीलैंड",
    "NAME_HU": "Zeeland",
    "NAME_ID": "Zeeland",
    "NAME_IT": "Zelanda",
    "NAME_JA": "ゼーラント州",
    "NAME_KO": "제일란트 주",
    "NAME_NL": "Zeeland",
    "NAME_PL": "Zelandia",
    "NAME_PT": "Zelândia",
    "NAME_RU": "Зеландия",
    "NAME_SV": "Zeeland",
    "NAME_TR": "Zelanda",
    "NAME_VI": "Zeeland",
    "NAME_ZH": "泽兰省",
    "NE_ID": 1159310959
}