{
    "FEATURECLA": "Admin-1 scale rank",
    "SCALERANK": 2,
    "ADM1_CODE": "USA-3527",
    "DISS_ME": 3527,
    "ISO_3166_2": "US-WY",
    "WIKIPEDIA": "http://en.wikipedia.org/wiki/Wyoming",
    "ISO_A2": "US",
    "ADM0_SR": 1,
    "NAME": "Wyoming",
    "NAME_ALT": "WY|Wyo.",
    "NAME_LOCAL": null,
    "TYPE": "State",
    "TYPE_EN": "State",
    "CODE_LOCAL": "US56",
    "CODE_HASC": "US.WY",
    "NOTE": null,
    "HASC_MAYBE": null,
    "REGION": "West",
    "REGION_COD": null,
    "PROVNUM_NE": 0,
    "GADM_LEVEL": 1,
    "CHECK_ME": 20,
    "DATARANK": 1,
    "ABBREV": "Wyo.",
    "POSTAL": "WY",
    "AREA_SQKM": 0,
    "SAMEASCITY": -99,
    "LABELRANK": 0,
    "NAME_LEN": 7,
    "MAPCOLOR9": 1,
    "MAPCOLOR13": 1,
    "FIPS": "US56",
    "FIPS_ALT": null,
    "WOE_ID": 2347609,
    "WOE_LABEL": "Wyoming, US, United States",
    "WOE_NAME": "Wyoming",
    "LATITUDE": 42.9999,
    "LONGITUDE": -107.552,
    "SOV_A3": "US1",
    "ADM0_A3": "USA",
    "ADM0_LABEL": 2,
    "ADMIN": "United States of America",
    "GEONUNIT": "United States of America",
    "GU_A3": "USA",
    "GN_ID": 5843591,
    "GN_NAME": "Wyoming",
    "GNS_ID": -1,
    "GNS_NAME": null,
    "GN_LEVEL": 1,
    "GN_REGION": null,
    "GN_A1_CODE": "US.WY",
    "REGION_SUB": "Mountain",
    "SUB_CODE": null,
    "GNS_LEVEL": -1,
    "GNS_LANG": null,
    "GNS_ADM1": null,
    "GNS_REGION": null,
    "MIN_LABEL": 3.5,
    "MAX_LABEL": 7.5,
    "MIN_ZOOM": 2,
    "WIKIDATAID": "Q1214",
    "NAME_AR": "وايومنغ",
    "NAME_BN": "ওয়াইয়োমিং",
    "NAME_DE": "Wyoming",
    "NAME_EN": "Wyoming",
    "NAME_ES": "Wyoming",
    "NAME_FR": "Wyoming",
    "NAME_EL": "Ουαϊόμινγκ",
    "NAME_HI": "वायोमिंग",
    "NAME_HU": "Wyoming",
    "NAME_ID": "Wyoming",
    "NAME_IT": "Wyoming",
    "NAME_JA": "ワイオミング州",
    "NAME_KO": "와이오밍주",
    "NAME_NL": "Wyoming",
    "NAME_PL": "Wyoming",
    "NAME_PT": "Wyoming",
    "NAME_RU": "Вайоминг",
    "NAME_SV": "Wyoming",
    "NAME_TR": "Wyoming",
    "NAME_VI": "Wyoming",
    "NAME_ZH": "怀俄明州",
    "NE_ID": 1159315351
}