{
    "FEATURECLA": "Admin-1 scale rank",
    "SCALERANK": 9,
    "ADM1_CODE": "UGA-5614",
    "DISS_ME": 5614,
    "ISO_3166_2": "UG-230",
    "WIKIPEDIA": null,
    "ISO_A2": "UG",
    "ADM0_SR": 1,
    "NAME": "Namayingo",
    "NAME_ALT": null,
    "NAME_LOCAL": null,
    "TYPE": "District",
    "TYPE_EN": "District",
    "CODE_LOCAL": null,
    "CODE_HASC": "UG.NY",
    "NOTE": null,
    "HASC_MAYBE": null,
    "REGION": "Eastern",
    "REGION_COD": "UGA-EST",
    "PROVNUM_NE": 20022,
    "GADM_LEVEL": 1,
    "CHECK_ME": 0,
    "DATARANK": 5,
    "ABBREV": null,
    "POSTAL": "BG",
    "AREA_SQKM": 0,
    "SAMEASCITY": -99,
    "LABELRANK": 9,
    "NAME_LEN": 9,
    "MAPCOLOR9": 6,
    "MAPCOLOR13": 4,
    "FIPS": "UGG7",
    "FIPS_ALT": null,
    "WOE_ID": -20070454,
    "WOE_LABEL": null,
    "WOE_NAME": null,
    "LATITUDE": 0.246262,
    "LONGITUDE": 33.8049,
    "SOV_A3": "UGA",
    "ADM0_A3": "UGA",
    "ADM0_LABEL": 2,
    "ADMIN": "Uganda",
    "GEONUNIT": "Uganda",
    "GU_A3": "UGA",
    "GN_ID": 8030575,
    "GN_NAME": "Namayingo District",
    "GNS_ID": 11074796,
    "GNS_NAME": "Namayingo District",
    "GN_LEVEL": 2,
    "GN_REGION": null,
    "GN_A1_CODE": "UG.G7",
    "REGION_SUB": null,
    "SUB_CODE": "UG20",
    "GNS_LEVEL": 1,
    "GNS_LANG": "fra",
    "GNS_ADM1": "UG24",
    "GNS_REGION": null,
    "MIN_LABEL": 10,
    "MAX_LABEL": 11,
    "MIN_ZOOM": 10,
    "WIKIDATAID": "Q1114915",
    "NAME_AR": "مقاطعة نامايينغو",
    "NAME_BN": "নামাইংগো জেলা",
    "NAME_DE": "Namayingo-Distrikt",
    "NAME_EN": "Namayingo District",
    "NAME_ES": "Distrito de Namayingo",
    "NAME_FR": "Namayingo",
    "NAME_EL": "Ναμαγίνγκο",
    "NAME_HI": "नमयिंगो जिला",
    "NAME_HU": null,
    "NAME_ID": "Distrik Namayingo",
    "NAME_IT": "Namayingo",
    "NAME_JA": "ナマインゴ県",
    "NAME_KO": "나마잉고 구",
    "NAME_NL": "Namayingo",
    "NAME_PL": "Dystrykt Namayingo",
    "NAME_PT": "Namayingo",
    "NAME_RU": "Намайинго",
    "NAME_SV": "Namayingodistriktet",
    "NAME_TR": "Namayingo District",
    "NAME_VI": "Quận Namayingo",
    "NAME_ZH": "納馬因戈區",
    "NE_ID": 1159317393
}