{
    "FEATURECLA": "Admin-1 scale rank",
    "SCALERANK": 10,
    "ADM1_CODE": "MKD-2913",
    "DISS_ME": 2913,
    "ISO_3166_2": "MK-79",
    "WIKIPEDIA": null,
    "ISO_A2": "MK",
    "ADM0_SR": 1,
    "NAME": "Čair",
    "NAME_ALT": "Cair",
    "NAME_LOCAL": null,
    "TYPE": "Municipality",
    "TYPE_EN": "Municipality",
    "CODE_LOCAL": null,
    "CODE_HASC": "MK.CI",
    "NOTE": null,
    "HASC_MAYBE": null,
    "REGION": "Greater Skopje",
    "REGION_COD": null,
    "PROVNUM_NE": 20077,
    "GADM_LEVEL": 1,
    "CHECK_ME": 11,
    "DATARANK": 8,
    "ABBREV": null,
    "POSTAL": "CI",
    "AREA_SQKM": 0,
    "SAMEASCITY": -99,
    "LABELRANK": 10,
    "NAME_LEN": 4,
    "MAPCOLOR9": 7,
    "MAPCOLOR13": 3,
    "FIPS": "MKA3",
    "FIPS_ALT": null,
    "WOE_ID": 24550752,
    "WOE_LABEL": null,
    "WOE_NAME": "Cair Municipality",
    "LATITUDE": 41.9946,
    "LONGITUDE": 21.4367,
    "SOV_A3": "MKD",
    "ADM0_A3": "MKD",
    "ADM0_LABEL": 5,
    "ADMIN": "Macedonia",
    "GEONUNIT": "Macedonia",
    "GU_A3": "MKD",
    "GN_ID": 863836,
    "GN_NAME": "Opstina Cair",
    "GNS_ID": 0,
    "GNS_NAME": null,
    "GN_LEVEL": 1,
    "GN_REGION": null,
    "GN_A1_CODE": "MK.C8",
    "REGION_SUB": null,
    "SUB_CODE": null,
    "GNS_LEVEL": 0,
    "GNS_LANG": null,
    "GNS_ADM1": null,
    "GNS_REGION": null,
    "MIN_LABEL": 10,
    "MAX_LABEL": 11,
    "MIN_ZOOM": 10,
    "WIKIDATAID": "Q1419314",
    "NAME_AR": null,
    "NAME_BN": null,
    "NAME_DE": "Opština Čair",
    "NAME_EN": "Čair Municipality",
    "NAME_ES": "Municipalidad de Čair",
    "NAME_FR": "Tchaïr",
    "NAME_EL": null,
    "NAME_HI": null,
    "NAME_HU": null,
    "NAME_ID": null,
    "NAME_IT": "Čair",
    "NAME_JA": null,
    "NAME_KO": "차이르 시",
    "NAME_NL": "Čair",
    "NAME_PL": null,
    "NAME_PT": null,
    "NAME_RU": null,
    "NAME_SV": "Čair",
    "NAME_TR": null,
    "NAME_VI": null,
    "NAME_ZH": "查伊尔区",
    "NE_ID": 1159314437
}