{
    "FEATURECLA": "Admin-1 scale rank",
    "SCALERANK": 10,
    "ADM1_CODE": "MDV-5223",
    "DISS_ME": 5223,
    "ISO_3166_2": "MV-07",
    "WIKIPEDIA": null,
    "ISO_A2": "MV",
    "ADM0_SR": 5,
    "NAME": "Haa Alifu",
    "NAME_ALT": "Thiladhunmathi Uthuruburi",
    "NAME_LOCAL": null,
    "TYPE": "Atoll",
    "TYPE_EN": "Atoll",
    "CODE_LOCAL": "A",
    "CODE_HASC": "MV.HA",
    "NOTE": null,
    "HASC_MAYBE": null,
    "REGION": "Upper North",
    "REGION_COD": "MV-UN",
    "PROVNUM_NE": 0,
    "GADM_LEVEL": 0,
    "CHECK_ME": 0,
    "DATARANK": 10,
    "ABBREV": "HA",
    "POSTAL": "HA",
    "AREA_SQKM": 0,
    "SAMEASCITY": -99,
    "LABELRANK": 20,
    "NAME_LEN": 9,
    "MAPCOLOR9": 1,
    "MAPCOLOR13": 7,
    "FIPS": null,
    "FIPS_ALT": null,
    "WOE_ID": 20070312,
    "WOE_LABEL": "Haa Alifu, MV, Maldives",
    "WOE_NAME": "Haa Alifu",
    "LATITUDE": 7.02774,
    "LONGITUDE": 72.9797,
    "SOV_A3": "MDV",
    "ADM0_A3": "MDV",
    "ADM0_LABEL": 5,
    "ADMIN": "Maldives",
    "GEONUNIT": "Maldives",
    "GU_A3": "MDV",
    "GN_ID": 1282294,
    "GN_NAME": "Haa Alifu Atholhu",
    "GNS_ID": 0,
    "GNS_NAME": null,
    "GN_LEVEL": 1,
    "GN_REGION": null,
    "GN_A1_CODE": "MV.36",
    "REGION_SUB": null,
    "SUB_CODE": null,
    "GNS_LEVEL": 0,
    "GNS_LANG": null,
    "GNS_ADM1": null,
    "GNS_REGION": null,
    "MIN_LABEL": 10,
    "MAX_LABEL": 11,
    "MIN_ZOOM": 10,
    "WIKIDATAID": "Q2360912",
    "NAME_AR": "آتول ها ألف",
    "NAME_BN": "হা আলিফ  এটল",
    "NAME_DE": "Haa Alif",
    "NAME_EN": "Haa Alif Atoll",
    "NAME_ES": "Atolón Haa Alif",
    "NAME_FR": "Haa Alifu",
    "NAME_EL": "Χαά Αλίφ Ατόλ",
    "NAME_HI": "हा अलिफ एटोल",
    "NAME_HU": "Északi-Tiladummati-atoll",
    "NAME_ID": "Atol Haa Alif",
    "NAME_IT": "Atollo Haa Alif",
    "NAME_JA": "ハーアリフ環礁",
    "NAME_KO": "하알리프 환초",
    "NAME_NL": "Haa Alif-atol",
    "NAME_PL": "Haa Alif",
    "NAME_PT": "Haa Alif Atoll",
    "NAME_RU": "Хаа-Алиф",
    "NAME_SV": "Haa Alifu Atholhu",
    "NAME_TR": "Haa Alif Atoll",
    "NAME_VI": "Haa Alif Atoll",
    "NAME_ZH": "哈阿里夫環礁",
    "NE_ID": 1159307979
}